factory_edsl/__init__.py
factory_edsl/factory.py
factoryboy_edsl-0.1.0.dist-info/LICENSE
factoryboy_edsl-0.1.0.dist-info/METADATA
factoryboy_edsl-0.1.0.dist-info/WHEEL
factoryboy_edsl-0.1.0.dist-info/RECORD
