Metadata-Version: 2.1
Name: factoryboy-edsl
Version: 0.1.0
Summary: Factoryboy helpers for Elasticsearch-dsl
Home-page: https://github.com/etchegom/factoryboy-edsl
License: MIT
Keywords: elasticsearch-dsl,elasticsearch,factory-boy,factoryboy
Author: Matthieu Etchegoyen
Author-email: etchegom@gmail.com
Maintainer: Matthieu Etchegoyen
Maintainer-email: etchegom@gmail.com
Requires-Python: >=3.8,<4.0
Classifier: Environment :: Web Environment
Classifier: Intended Audience :: Developers
Classifier: License :: OSI Approved :: MIT License
Classifier: Natural Language :: English
Classifier: Operating System :: OS Independent
Classifier: Programming Language :: Python :: 3
Classifier: Programming Language :: Python :: 3.8
Classifier: Programming Language :: Python :: 3.9
Classifier: Programming Language :: Python :: 3.10
Classifier: Programming Language :: Python :: 3.11
Classifier: Programming Language :: Python :: 3 :: Only
Requires-Dist: elasticsearch-dsl (>=8.9.0,<9.0.0)
Requires-Dist: factory-boy (>=3.2,<4.0)
Project-URL: Documentation, https://github.com/etchegom/factoryboy-edsl
Project-URL: Repository, https://github.com/etchegom/factoryboy-edsl
